redque/__init__.py
redque-0.1.0.dist-info/LICENSE
redque-0.1.0.dist-info/METADATA
redque-0.1.0.dist-info/WHEEL
redque-0.1.0.dist-info/top_level.txt
redque-0.1.0.dist-info/RECORD
