Metadata-Version: 2.1
Name: redque
Version: 0.1.0
Summary: A distributed queue based on Redis.
Home-page: https://github.com/shixiongfei/redque
Author: Xiongfei Shi
Author-email: jenson.shixf@gmail.com
Maintainer: Xiongfei Shi
Maintainer-email: jenson.shixf@gmail.com
License: UNKNOWN
Keywords: Redis,Queue
Platform: UNKNOWN
Classifier: Intended Audience :: Developers
Classifier: License :: OSI Approved :: Apache Software License
Classifier: Operating System :: OS Independent
Classifier: Programming Language :: Python
Classifier: Topic :: Software Development :: Libraries :: Python Modules
Classifier: Topic :: Software Development :: Object Brokering
Classifier: Topic :: System :: Distributed Computing
Requires-Dist: redis
